strumpf/__init__.py
strumpf/cli.py
strumpf/client.py
strumpf/core.py
strumpf/utils.py
strumpf-0.3.5.dist-info/DESCRIPTION.rst
strumpf-0.3.5.dist-info/METADATA
strumpf-0.3.5.dist-info/RECORD
strumpf-0.3.5.dist-info/WHEEL
strumpf-0.3.5.dist-info/entry_points.txt
strumpf-0.3.5.dist-info/metadata.json
strumpf-0.3.5.dist-info/top_level.txt
