Metadata-Version: 2.0
Name: strumpf
Version: 0.3.5
Summary: Skymind test resource management for paunchy files
Home-page: https://github.com/deeplearning4j/strumpf
Author: Max Pumperla
Author-email: max@skymind.io
License: Apache
Platform: UNKNOWN
Classifier: Development Status :: 3 - Alpha
Classifier: Intended Audience :: Developers
Classifier: Environment :: Console
Classifier: License :: OSI Approved :: Apache Software License
Classifier: Operating System :: OS Independent
Classifier: Programming Language :: Python
Classifier: Programming Language :: Python :: 3
Provides-Extra: tests
Requires-Dist: argcomplete
Requires-Dist: azure
Requires-Dist: click
Requires-Dist: requests
Provides-Extra: tests
Requires-Dist: mock; extra == 'tests'
Requires-Dist: pytest; extra == 'tests'
Requires-Dist: pytest-cov; extra == 'tests'
Requires-Dist: pytest-pep8; extra == 'tests'
